fastchrf-0.1.0.dist-info/METADATA
fastchrf-0.1.0.dist-info/WHEEL
fastchrf-0.1.0.dist-info/license_files/LICENSE
fastchrf/__init__.py
fastchrf/fastchrf.pypy39-pp73-x86-linux-gnu.so
fastchrf-0.1.0.dist-info/RECORD
